glances/__init__.py
glances/__main__.py
glances/actions.py
glances/amps_list.py
glances/api.py
glances/attribute.py
glances/client.py
glances/client_browser.py
glances/config.py
glances/cpu_percent.py
glances/event.py
glances/events_list.py
glances/filter.py
glances/folder_list.py
glances/globals.py
glances/history.py
glances/logger.py
glances/main.py
glances/outdated.py
glances/password.py
glances/password_list.py
glances/ports_list.py
glances/processes.py
glances/programs.py
glances/secure.py
glances/server.py
glances/servers_list.py
glances/servers_list_dynamic.py
glances/servers_list_static.py
glances/snmp.py
glances/standalone.py
glances/stats.py
glances/stats_client.py
glances/stats_client_snmp.py
glances/stats_server.py
glances/stats_streamer.py
glances/thresholds.py
glances/timer.py
glances/web_list.py
glances/webserver.py
glances/amps/__init__.py
glances/amps/amp.py
glances/amps/default/__init__.py
glances/amps/nginx/__init__.py
glances/amps/systemd/__init__.py
glances/amps/systemv/__init__.py
glances/exports/__init__.py
glances/exports/export.py
glances/exports/glances_cassandra/__init__.py
glances/exports/glances_couchdb/__init__.py
glances/exports/glances_csv/__init__.py
glances/exports/glances_duckdb/__init__.py
glances/exports/glances_elasticsearch/__init__.py
glances/exports/glances_graph/__init__.py
glances/exports/glances_graphite/__init__.py
glances/exports/glances_influxdb/__init__.py
glances/exports/glances_influxdb2/__init__.py
glances/exports/glances_influxdb3/__init__.py
glances/exports/glances_json/__init__.py
glances/exports/glances_kafka/__init__.py
glances/exports/glances_mongodb/__init__.py
glances/exports/glances_mqtt/__init__.py
glances/exports/glances_opentsdb/__init__.py
glances/exports/glances_prometheus/__init__.py
glances/exports/glances_rabbitmq/__init__.py
glances/exports/glances_restful/__init__.py
glances/exports/glances_riemann/__init__.py
glances/exports/glances_statsd/__init__.py
glances-4.4.1.dist-info/licenses/AUTHORS
glances-4.4.1.dist-info/licenses/COPYING
glances-4.4.1.dist-info/METADATA
glances-4.4.1.dist-info/WHEEL
glances-4.4.1.dist-info/entry_points.txt
glances-4.4.1.dist-info/top_level.txt
glances-4.4.1.dist-info/RECORD
