Metadata-Version: 2.4
Name: Glances
Version: 4.4.1
Summary: A cross-platform curses-based monitoring tool
Author-email: Nicolas Hennion <nicolas@nicolargo.com>
License: LGPLv3
Project-URL: Homepage, https://github.com/nicolargo/glances
Keywords: cli,curses,monitoring,system
Classifier: Development Status :: 5 - Production/Stable
Classifier: Environment :: Console :: Curses
Classifier: Environment :: Web Environment
Classifier: Framework :: FastAPI
Classifier: Intended Audience :: Developers
Classifier: Intended Audience :: End Users/Desktop
Classifier: Intended Audience :: System Administrators
Classifier: License :: OSI Approved :: GNU Lesser General Public License v3 (LGPLv3)
Classifier: Operating System :: OS Independent
Classifier: Programming Language :: Python :: 3
Classifier: Programming Language :: Python :: 3.9
Classifier: Programming Language :: Python :: 3.10
Classifier: Programming Language :: Python :: 3.11
Classifier: Programming Language :: Python :: 3.12
Classifier: Programming Language :: Python :: 3.13
Classifier: Programming Language :: Python :: 3.14
Classifier: Topic :: System :: Monitoring
Requires-Python: >=3.9
License-File: COPYING
License-File: AUTHORS
Requires-Dist: defusedxml
Requires-Dist: packaging
Requires-Dist: psutil>=5.6.7
Requires-Dist: windows-curses; platform_system == "Windows"
Requires-Dist: shtab; platform_system != "Windows"
Requires-Dist: jinja2
Provides-Extra: action
Requires-Dist: chevron; extra == "action"
Provides-Extra: all
Requires-Dist: glances[action,browser,cloud,containers,export,gpu,graph,ip,raid,sensors,smart,snmp,sparklines,web,wifi]; extra == "all"
Provides-Extra: browser
Requires-Dist: zeroconf; extra == "browser"
Provides-Extra: cloud
Requires-Dist: requests; extra == "cloud"
Provides-Extra: containers
Requires-Dist: docker>=6.1.1; extra == "containers"
Requires-Dist: packaging; extra == "containers"
Requires-Dist: podman; extra == "containers"
Requires-Dist: python-dateutil; extra == "containers"
Requires-Dist: six; extra == "containers"
Provides-Extra: export
Requires-Dist: bernhard; extra == "export"
Requires-Dist: cassandra-driver; extra == "export"
Requires-Dist: elasticsearch; extra == "export"
Requires-Dist: graphitesender; extra == "export"
Requires-Dist: ibmcloudant; extra == "export"
Requires-Dist: influxdb-client; extra == "export"
Requires-Dist: influxdb>=1.0.0; extra == "export"
Requires-Dist: influxdb3-python; extra == "export"
Requires-Dist: kafka-python; extra == "export"
Requires-Dist: paho-mqtt; extra == "export"
Requires-Dist: pika; extra == "export"
Requires-Dist: potsdb; extra == "export"
Requires-Dist: prometheus_client; extra == "export"
Requires-Dist: psycopg[binary]; extra == "export"
Requires-Dist: pymongo; extra == "export"
Requires-Dist: pyzmq; extra == "export"
Requires-Dist: statsd; extra == "export"
Provides-Extra: gpu
Requires-Dist: nvidia-ml-py; extra == "gpu"
Provides-Extra: graph
Requires-Dist: pygal; extra == "graph"
Provides-Extra: ip
Requires-Dist: netifaces2; extra == "ip"
Provides-Extra: raid
Requires-Dist: pymdstat; extra == "raid"
Provides-Extra: sensors
Requires-Dist: batinfo; platform_system == "Linux" and extra == "sensors"
Provides-Extra: smart
Requires-Dist: pySMART.smartx; extra == "smart"
Provides-Extra: snmp
Requires-Dist: pysnmp-lextudio<6.3.1; extra == "snmp"
Provides-Extra: sparklines
Requires-Dist: sparklines; extra == "sparklines"
Provides-Extra: web
Requires-Dist: fastapi>=0.82.0; extra == "web"
Requires-Dist: requests; extra == "web"
Requires-Dist: uvicorn; extra == "web"
Provides-Extra: wifi
Requires-Dist: wifi; extra == "wifi"
Dynamic: license-file
